setup.cfg
setup.py
nyaa/__init__.py
nyaa/__main__.py
nyaa/webtorrent.py
nyaa/parsers/__init__.py
nyaa/parsers/bakabt.py
nyaa/parsers/classes.py
nyaa/parsers/masterani.py
nyaa/parsers/nyaa.py
nyaa_cli.egg-info/PKG-INFO
nyaa_cli.egg-info/SOURCES.txt
nyaa_cli.egg-info/dependency_links.txt
nyaa_cli.egg-info/entry_points.txt
nyaa_cli.egg-info/requires.txt
nyaa_cli.egg-info/top_level.txt