Metadata-Version: 1.1
Name: nyaa-cli
Version: 0.0.1.dev12
Summary: Anime Stream CLI for torrents and online videos
Home-page: https://github.com/setr/animestreamer-cli
Author: Neil Okhandiar
Author-email: nokhand@gmail.com
License: GPLv3
Keywords: webtorrent anime
Platform: UNKNOWN
Classifier: Development Status :: 3 - Alpha
Classifier: Intended Audience :: End Users/Desktop
Classifier: License :: OSI Approved :: GNU General Public License v3 (GPLv3)
Classifier: Programming Language :: Python :: 2
Classifier: Programming Language :: Python :: 2.7
Classifier: Programming Language :: Python :: 3.3
Classifier: Programming Language :: Python :: 3.4
Classifier: Programming Language :: Python :: 3.5
